doi2ietf/__init__.py
doi2ietf/command_line.py
doi2ietf/utils.py
doi2ietf-0.1.2.dist-info/LICENSE.txt
doi2ietf-0.1.2.dist-info/METADATA
doi2ietf-0.1.2.dist-info/WHEEL
doi2ietf-0.1.2.dist-info/entry_points.txt
doi2ietf-0.1.2.dist-info/top_level.txt
doi2ietf-0.1.2.dist-info/RECORD
