Metadata-Version: 2.1
Name: doi2ietf
Version: 0.1.2
Summary: Converts DOI metadata into IETF BibXML format
Home-page: https://github.com/ietf-ribose/doi2ietf-py
Author: Ribose
Author-email: open.source@ribose.com
License: MIT
Project-URL: Documentation, https://github.com/ietf-ribose/doi2ietf-py
Project-URL: Source, https://github.com/ietf-ribose/doi2ietf-py
Project-URL: Tracker, https://github.com/ietf-ribose/doi2ietf-py/issues
Platform: UNKNOWN
Classifier: Programming Language :: Python :: 3
Classifier: License :: OSI Approved :: MIT License
Classifier: Operating System :: OS Independent
Requires-Python: >=3.6
License-File: LICENSE.txt
Requires-Dist: pyyaml
Requires-Dist: requests
Requires-Dist: requests-cache
Requires-Dist: simplejson
